ds4biz_commons/__init__.py
ds4biz_commons/apps/__init__.py
ds4biz_commons/business/__init__.py
ds4biz_commons/business/annotations.py
ds4biz_commons/business/apiclients.py
ds4biz_commons/business/decorators.py
ds4biz_commons/business/factories.py
ds4biz_commons/business/observers.py
ds4biz_commons/business/pools.py
ds4biz_commons/business/sampling.py
ds4biz_commons/config/AppConfig.py
ds4biz_commons/config/__init__.py
ds4biz_commons/dao/__init__.py
ds4biz_commons/dao/serializers.py
ds4biz_commons/examples/__init__.py
ds4biz_commons/examples/decorators_example.py
ds4biz_commons/examples/object_dict_example.py
ds4biz_commons/examples/sampling_example.py
ds4biz_commons/examples/tm_example.py
ds4biz_commons/examples/urlrequest_example.py
ds4biz_commons/model/__init__.py
ds4biz_commons/model/taskmanagement.py
ds4biz_commons/model/versioning.py
ds4biz_commons/resources/__init__.py
ds4biz_commons/services/__init__.py
ds4biz_commons/services/services.py
ds4biz_commons/test/__init__.py
ds4biz_commons/test/decorators_test.py
ds4biz_commons/test/test_objectdict.py
ds4biz_commons/test/test_url_creation.py
ds4biz_commons/utils/__init__.py
ds4biz_commons/utils/cache.py
ds4biz_commons/utils/config_utils.py
ds4biz_commons/utils/dict_utils.py
ds4biz_commons/utils/function_utils.py
ds4biz_commons/utils/gen_utils.py
ds4biz_commons/utils/loggerutils.py
ds4biz_commons/utils/requests_utils.py
ds4biz_commons/utils/submodules.py
ds4biz_commons/utils/wrappers.py
ds4biz_commons-0.0.8.dist-info/METADATA
ds4biz_commons-0.0.8.dist-info/WHEEL
ds4biz_commons-0.0.8.dist-info/top_level.txt
ds4biz_commons-0.0.8.dist-info/RECORD
